Workbook

Sheet P&L
A1: DIGITAL & PUBLISHING DIVISION
A2: AI SUMMIT
C3: ACTUAL USD | D3: ACTUAL ZWG | E3: BUDGETED | F3: BUD VAR
A4: REVENUE: | C4: USD | D4: ZWG | E4: USD
A5: REVENUE | C5: =REVENUE!B16 -> 31250.58 | D5: 0 | E5: =REVENUE!E16 -> 77943.723
A6: TOTAL REVENUE | C6: =SUM(C5:C5) -> 31250.58 | D6: =SUM(D5:D5) -> 0 | E6: =SUM(E5) -> 77943.723 | F6: =C6/E6-1 -> -0.59906226
A7: EXPENDITURE
A8: VENUE , LUNCH AND DRINKS | C8: ='expenses '!B7 -> 8054.45 | E8: ='expenses '!F7 -> 40100
A9: PA SYSTEM | C9: ='expenses '!B8 -> 0 | D9: 0 | E9: ='expenses '!F9 -> 600
A10: MC | C10: ='expenses '!B9 -> 500 | E10: ='expenses '!F11 -> 5600
A11: GIFTS FOR SPEAKERS | C11: ='expenses '!B10 -> 0 | E11: ='expenses '!F12 -> 900
A12: PROGRAMS AND TICKETS PRINTING | E12: ='expenses '!F14 -> 300
A13: ENTERTAINMENT | E13: ='expenses '!F15 -> 0
A14: Accommodation | E14: 500
A17: TOTAL EXPENDITURE | C17: =SUM(C8:C10) -> 8554.45 | D17: =SUM(D8:D10) -> 0 | E17: =SUM(E8:E14) -> 48000 | F17: =C17/E17-1 -> -0.82178229
A19: Profit before Agency fee | C19: =C6-C17 -> 22696.13 | D19: =D6-D17 -> 0 | E19: =E6-E17 -> 29943.723 | F19: =C19/E19-1 -> -0.24204047
A20: Less Agency Fee
A21: Profit After Agency fee | C21: =C19-C20 -> 22696.13 | D21: =D19-D20 -> 0 | E21: =E19-E20 -> 29943.723 | F21: =C21/E21-1 -> -0.24204047
A23: Gross Profit Margin | C23: =C21/C6 -> 0.72626268 | D23: 0 | E23: =E21/E6 -> 0.38417106
A25: Remarks
A26: TO SHARE PROFITS WITH THE PARTNER

Sheet REVENUE
A1: AI SUMMIT
B2: ACTUAL | C2: ACTUAL | D2: ACTUAL | E2: BUDGET | H2: Signed Agreement | K2: Payment Details
A3: REVENUE FROM SPONSERS | B3: USD | C3: RATE | D3: ZIG | E3: USD | F3: US$ | H3: YES | I3: NO | K3: Rec: No | L3: Amount Paid: | N3: Contract #
F4: COMMENTS
A5: Client
A6: DELEGATES | B6: 0 | E6: 65025
A7: ECONET | B7: 12380.71 | E7: 0 | F7: PAID | Q7: POSTED
A8: NEC | B8: 1440 | E8: 5000 | F8: PAID | Q8: POSTED
A9: OLD MUTUAL | B9: 3898 | E9: 5000 | F9: PAID | Q9: POSTED REMAIN 1296
A10: DANDEMUTANDE | B10: 2500 | E10: 2500 | F10: SETOFF | Q10: POSTED
A11: NETONE | B11: 10875.71 | E11: 7500 | F11: PAID
A12: NSSA | B12: 5000 | E12: 5000 | F12: PAID | Q12: POSTED
A14: SUBTOTAL | B14: =SUM(B6:B13) -> 36094.42 | C14: =SUM(C7:C13) -> 0 | D14: =SUM(D7:D13) -> 0 | E14: =SUM(E6:E13) -> 90025 | F14: =SUM(F7:F13) -> 0 | L14: =SUM(L7:L13) -> 0
A16: GRAND TOTAL | B16: =B14/1.155 -> 31250.58 | C16: =C14 -> 0 | E16: =E14/1.155 -> 77943.723

Sheet expenses 
A2: AI SUMMIT
A4: EXPENSES: | B4: ACT | C4: RATE | D4: ACT | E4: ACT (RANDS) | F4: BUD (USD$) | G4: REMARKS
A6: VENUE AND SETUP
A7: VENUE, ACC, DINNER, CONFERENCE | B7: =1400+1494+1836.45+540+1319+1465 -> 8054.45 | F7: 40100 | G7: what is the basis?
A8: PA SYSTEM | F8: 0
A9: MC | B9: 500 | F9: 600 | G9: okay
A10: ENTERTAINMENT | F10: 500
A11: GIFTS FOR SPEAKERS | F11: 5600
A12: KEY SPEAKER APRECIATION | F12: 900
A13: DELEGATES PACKS | F13: 4550
A14: VENUE BRANDING | F14: 300
A15: TRANSPORT | F15: 0
G16: Is this covered by the venue?
G17: Is this covered by the venue?
G21: 0
A23: TOTAL EXPENDITURE | B23: =SUM(B7:B16) -> 8554.45 | C23: =SUM(C9:C9) -> 0 | D23: =SUM(D9:D9) -> 0 | E23: =SUM(E9:E9) -> 0 | F23: =SUM(F7:F22) -> 52550

Sheet PROFIT SHARING
A1: Zimbabwe Newspapers (1980) Ltd
A3: Harare Branch
A5: Industry & University Together Summit
A8: Period | B8: Invoice | C8: REVENUE | D8: EXPENSES | E8: PROFIT/LOSS | F8: ZIMPAPERS 70% PORTION | G8: MEMSHA 30% PORTION | H8: TOTAL
A9: USD | C9: ='P&L'!#REF! -> #REF! | D9: ='P&L'!#REF! -> #REF! | E9: =C9-D9 -> #REF! | F9: =E9*0.7 -> #REF! | G9: =E9*0.3 -> #REF! | H9: =F9+G9 -> #REF!
A10: ZWG | C10: ='P&L'!#REF! -> #REF! | D10: 0 | E10: =C10-D10 -> #REF! | F10: =E10*0.7 -> #REF! | G10: =E10*0.3 -> #REF! | H10: =F10+G10 -> #REF!
A12: LESS: payments not yet received
A13: Netone | C13: 4347.8261
A15: Total | C15: =C9-C13 -> #REF! | D15: =SUM(D9:D14) -> #REF! | E15: =C15-D15 -> #REF! | F15: =SUM(F9:F14) -> #REF! | G15: =SUM(G9:G14) -> #REF!
G17: AMOUNT PAYABLE TO MEMSHA
G18: USD | H18: ZWG
E19: Amount payable to Memsha before deducting unpaid recs | G19: =G9 -> #REF! | H19: =G10 -> #REF! | K19: s
E21: Less upaid revenue-netone portion (4347.83/5647.83) | F21: =C13/C9 -> #REF! | G21: =F21*G19 -> #REF!
E23: Amount payable to Memsha after deducting unpaid recs | G23: =G19-G21 -> #REF! | H23: =H19-H21 -> #REF!
A27: Prepared by | B27: …………………………………………………………… | D27: ……………………………………………………………
A30: Checked by | B30: …………………………………………………………. | D30: ………………………………………………………….
A33: Approved by | B33: …………………………………………………………. | D33: ………………………………………………………….
